tasker_cli/__init__.py
tasker_cli/table.py
tasker_cli-0.0.2.dist-info/LICENSE
tasker_cli-0.0.2.dist-info/METADATA
tasker_cli-0.0.2.dist-info/WHEEL
tasker_cli-0.0.2.dist-info/top_level.txt
tasker_cli-0.0.2.dist-info/RECORD
